flask_pywebpush.py
Flask_pyWebPush-1.1.dist-info/LICENSE
Flask_pyWebPush-1.1.dist-info/METADATA
Flask_pyWebPush-1.1.dist-info/WHEEL
Flask_pyWebPush-1.1.dist-info/top_level.txt
Flask_pyWebPush-1.1.dist-info/RECORD
