Metadata-Version: 2.1
Name: Flask-pyWebPush
Version: 1.1
Summary: A clean interface to pywebpush from Flask
Home-page: https://github.com/illright/flask-pywebpush
Author: Lev Chelyadinov
Author-email: leva181777@gmail.com
License: MIT
Platform: any
Classifier: Environment :: Web Environment
Classifier: Intended Audience :: Developers
Classifier: License :: OSI Approved :: BSD License
Classifier: Operating System :: OS Independent
Classifier: Programming Language :: Python
Classifier: Topic :: Internet :: WWW/HTTP :: Dynamic Content
Classifier: Topic :: Software Development :: Libraries :: Python Modules
Requires-Python: >= 3.6
Requires-Dist: Flask
Requires-Dist: pywebpush
